.gitignore
LICENSE
README.md
__init__.py
project.yml
requirements.txt
setup.py
.github/workflows/python-app.yml
configs/base_config.cfg
configs/config.cfg
denomme/name.py
denomme.egg-info/PKG-INFO
denomme.egg-info/SOURCES.txt
denomme.egg-info/dependency_links.txt
denomme.egg-info/requires.txt
denomme.egg-info/top_level.txt
nbs/nb-stripout.py
nbs/train-denomme.ipynb
nbs/using_denomme.ipynb
scripts/__init__.py
scripts/convert.py
scripts/convert_to_spacy.py
tests/test_denomme.py