Metadata-Version: 2.1
Name: denomme
Version: 0.3.6
Summary: Name detection using spacy
Home-page: https://github.com/meghanabhange/denomme.git
Author: Meghana Bhange
Author-email: meghanabhange@hey.com
License: MIT
Platform: UNKNOWN
